{
  "personalInfo": {
    "name": "Votre Nom",
    "title": "Développeur Full Stack",
    "email": "votre.email@example.com",
    "phone": "+33 6 12 34 56 78",
    "location": "Paris, France",
    "linkedin": "linkedin.com/in/votre-profil",
    "github": "github.com/votre-username",
    "website": "votre-site.com"
  },
  "summary": "Développeur passionné avec X années d'expérience dans le développement d'applications web modernes. Spécialisé en React, Next.js et Node.js.",
  "experiences": [
    {
      "id": "exp-1",
      "title": "Développeur Full Stack",
      "company": "Slib",
      "location": "Lyon, France",
      "period": "Jan 2025 - present",
      "description": "Développement d'applications web Angular | Java",
      "details": [
        "Création from scratch d'une application web complète pour la gestion du vote CSE",
        "Choix des technologies adaptées aux besoins du projet",
        "Gestion de projet, travail d'équipe",
        "Mise en production dans un environnement sécurisé"
      ],
      "technologies": ["Angular", "Java", "SpringBoot", "PostgreSQL", "Docker", "Jenkins", "XlDeploy"]
    },
    {
      "id": "exp-2",
      "title": "Développeur Stagiaire",
      "company": "Bill Apps",
      "location": "Lyon, France",
      "period": "juil 2024 - jan 2025",
      "description": "Création d'interfaces utilisateur modernes et responsives",
      "details": [
        "Développement de composants réutilisables avec React",
        "Intégration d'APIs REST",
        "Création d'une application mobile React Native",
        "Acclimatation aux applications en microservices",
        "Travail en méthode agile"
      ],
      "technologies": ["React", "Redux", "NodeJs", "ReactNative"]
    },
    {
      "id": "exp-3",
      "title": "Militaire du rang",
      "company": "Armée de Terre | 3ème RPIMA",
      "location": "Carcassonne, France",
      "period": "2020 -",
      "description": "Travail d'équipe, discipline et résilience",
      "details": [
        "Apprentissage des valeurs militaires fondamentales",
        "Mise en oeuvre de stratégies de communication efficaces",
        "Gestion du stress et adaptation rapide",
        "Leadership et esprit d'équipe"
      ]
    }
  ],
  "education": [
    {
      "id": "edu-1",
      "degree": "Master en Informatique",
      "school": "Université de Paris",
      "location": "Paris, France",
      "period": "2016 - 2018",
      "description": "Spécialisation en développement web et architecture logicielle"
    },
    {
      "id": "edu-2",
      "degree": "Licence en Informatique",
      "school": "Université de Lyon",
      "location": "Lyon, France",
      "period": "2013 - 2016"
    }
  ],
  "projects": [
    {
      "id": "proj-1",
      "title": "ChessClub",
      "description": "Mise en place d'une application Web pour jouer aux échecs contre Stockfish, hébergement sur mon propre serveur.",
      "technologies": ["Svelte", "Rust", "Sqlite", "Docker"],
      "link": "chess.rdevs.fr",
      "github": "github.com/rgeral/chess",
      "highlights": [
        "Envie d'apprendre de nouvelles technologies",
        "Apprendre a heberger et deployer une application sur un serveur personnel",
        "Optimisation des performances pour une expérience utilisateur fluide"
      ]
    },
    {
      "id": "proj-2",
      "title": "Serveur de Streaming Multimédia",
      "description": "Mise en place d'un serveur de streaming multimédia pour diffuser des films/séries via Plex",
      "technologies": ["Script Bash", "Plex", "Docker", "Nginx", "cloudflare"],
      "highlights": [
        "Comprendre les bases du streaming multimédia",
        "Communication entre 6 services différents",
        "Mise en place d'un système sécurisé et performant pour plusieurs utilisateurs"
      ]
    },
    {
      "id": "proj-3",
      "title": "Projet en cours : RunInColor",
      "description": "Création d'une application mobile de running ludique et colorée pour encourager l'activité physique.",
      "technologies": ["Dart", "Go", "Docker"],
      "link": "https://github.com/Rgeral/RuninColor",
      "highlights": [
        "Découverte nouvelles technologies mobiles",
        "Hébergement d'une API en Go",
        "Perfectionnement CI et test unitaires"
      ]
    }
  ],
  "skills": [
    {
      "category": "Frontend",
      "items": ["Angular", "React", "Svelte", "Dart"]
    },
    {
      "category": "Backend",
      "items": ["Node.js", "Express", "Java", "SpringBoot", "Rust", "Go"]
    },
    {
      "category": "DevOps & Tools",
      "items": ["Git", "Docker", "CI/CD", "Jenkins", "XlDeploy", "Github Actions"]
    },
    {
      "category": "Langues",
      "items": ["Français (Natif)", "Anglais (Courant)"]
    }
  ]
}
